filingsdb/__init__.py
filingsdb/api_client.py
filingsdb/configuration.py
filingsdb/rest.py
filingsdb/api/__init__.py
filingsdb/api/document_api.py
filingsdb/api/filer_api.py
filingsdb/api/filing_api.py
filingsdb/api/form_api.py
filingsdb/models/__init__.py
filingsdb/models/document.py
filingsdb/models/document_info.py
filingsdb/models/document_response.py
filingsdb/models/error_response.py
filingsdb/models/filer.py
filingsdb/models/filer_list.py
filingsdb/models/filer_list_response.py
filingsdb/models/filing.py
filingsdb/models/filing_response.py
filingsdb/models/filings_list.py
filingsdb/models/filings_list_response.py
filingsdb/models/form.py
filingsdb/models/form_list.py
filingsdb/models/form_list_response.py
filingsdb/models/unauthorized_response.py
filingsdb-1.0.0.dist-info/LICENSE
filingsdb-1.0.0.dist-info/METADATA
filingsdb-1.0.0.dist-info/WHEEL
filingsdb-1.0.0.dist-info/top_level.txt
filingsdb-1.0.0.dist-info/RECORD
