Metadata-Version: 2.1
Name: filingsdb
Version: 1.0.0
Summary: filingsdb api library
Home-page: https://filingsdb.com
Author: FilingsDB
Author-email: info@filingsdb.com
License: MIT
Keywords: filingsdb,sec,library,filings,data,api
Platform: UNKNOWN
Classifier: Development Status :: 5 - Production/Stable
Classifier: Intended Audience :: Developers
Classifier: License :: OSI Approved :: MIT License
Classifier: Operating System :: OS Independent
Classifier: Programming Language :: Python
Classifier: Programming Language :: Python :: 2
Classifier: Programming Language :: Python :: 2.7
Classifier: Programming Language :: Python :: 3
Classifier: Programming Language :: Python :: 3.4
Classifier: Programming Language :: Python :: 3.5
Classifier: Programming Language :: Python :: 3.6
Classifier: Programming Language :: Python :: 3.7
Classifier: Programming Language :: Python :: Implementation :: PyPy
Classifier: Topic :: Software Development :: Libraries :: Python Modules
Requires-Python: >=2.7, !=3.0.*, !=3.1.*, !=3.2.*, !=3.3.*
Requires-Dist: certifi (>=2017.4.17)
Requires-Dist: python-dateutil (>=2.1)
Requires-Dist: six (>=1.10)
Requires-Dist: urllib3 (>=1.23)
